KvickStore/KvickStore.py
KvickStore/__init__.py
KvickStore-0.0.2.dist-info/LICENSE
KvickStore-0.0.2.dist-info/METADATA
KvickStore-0.0.2.dist-info/WHEEL
KvickStore-0.0.2.dist-info/top_level.txt
KvickStore-0.0.2.dist-info/RECORD
