Metadata-Version: 2.1
Name: KvickStore
Version: 0.0.2
Summary: A quick and simple key-value store for Python applications
Home-page: https://github.com/rm206/KvickStore
Author: Rishabh Mediratta
Author-email: panicpark60@gmail.com
Project-URL: Bug Tracker, https://github.com/rm206/KvickStore/issues
Project-URL: Changelog, https://github.com/rm206/KvickStore/releases
Classifier: Development Status :: 3 - Alpha
Classifier: Intended Audience :: Developers
Classifier: Topic :: Software Development :: Libraries :: Python Modules
Classifier: License :: OSI Approved :: MIT License
Classifier: Programming Language :: Python :: 3
Classifier: Programming Language :: Python :: 3.6
Classifier: Programming Language :: Python :: 3.7
Classifier: Programming Language :: Python :: 3.8
Classifier: Programming Language :: Python :: 3.9
Classifier: Operating System :: OS Independent
Requires-Python: >=3.6
License-File: LICENSE
